fora/__init__.py
fora/connection.py
fora/example_deploys.py
fora/inventory_wrapper.py
fora/loader.py
fora/logger.py
fora/main.py
fora/remote_settings.py
fora/types.py
fora/utils.py
fora/version.py
fora/connectors/__init__.py
fora/connectors/connector.py
fora/connectors/local.py
fora/connectors/ssh.py
fora/connectors/tunnel_connector.py
fora/connectors/tunnel_dispatcher.py
fora/operations/__init__.py
fora/operations/api.py
fora/operations/apt.py
fora/operations/files.py
fora/operations/git.py
fora/operations/local.py
fora/operations/pacman.py
fora/operations/pip.py
fora/operations/portage.py
fora/operations/postgres.py
fora/operations/system.py
fora/operations/systemd.py
fora/operations/utils.py
fora-2.1.7.dist-info/LICENSE
fora-2.1.7.dist-info/METADATA
fora-2.1.7.dist-info/WHEEL
fora-2.1.7.dist-info/entry_points.txt
fora-2.1.7.dist-info/top_level.txt
fora-2.1.7.dist-info/RECORD
