Metadata-Version: 2.1
Name: fora
Version: 2.1.7
Summary: A simple infrastructure and configuration management tool
Home-page: https://github.com/oddlama/fora
Author: oddlama
Author-email: oddlama@oddlama.org
License: MIT
Project-URL: Documentation, https://oddlama.gitbook.io/fora/
Project-URL: Source, https://github.com/oddlama/fora
Project-URL: Issues, https://github.com/oddlama/fora/issues
Keywords: ansible,configuration,deploy,deployment,infra,infrastructure,management,puppet,saltstack,config,fora
Classifier: Development Status :: 4 - Beta
Classifier: Environment :: Console
Classifier: Intended Audience :: Developers
Classifier: Intended Audience :: Information Technology
Classifier: Intended Audience :: System Administrators
Classifier: License :: OSI Approved :: MIT License
Classifier: Operating System :: POSIX :: Linux
Classifier: Programming Language :: Python :: 3 :: Only
Classifier: Programming Language :: Python :: 3.9
Classifier: Topic :: System :: Installation/Setup
Classifier: Topic :: System :: Systems Administration
Classifier: Topic :: Utilities
Requires-Python: >=3.9
License-File: LICENSE
Requires-Dist: jinja2
